duckdb_http/__init__.py
duckdb_http/dialect.py
duckdb_http-0.1.3.dist-info/METADATA
duckdb_http-0.1.3.dist-info/WHEEL
duckdb_http-0.1.3.dist-info/entry_points.txt
duckdb_http-0.1.3.dist-info/top_level.txt
duckdb_http-0.1.3.dist-info/RECORD
