Metadata-Version: 2.4
Name: duckdb_http
Version: 0.1.3
Summary: DuckDB HTTP dialect for SQLAlchemy
Author-email: Oraichain Labs <tu@orai.io>
License: MIT
Project-URL: Homepage, https://github.com/oraichain/duckdb-http.git
Project-URL: Repository, https://github.com/oraichain/duckdb-http.git
Requires-Python: >=3.8
Requires-Dist: duckdb==1.3.2
Requires-Dist: sqlalchemy==1.4.54
Requires-Dist: requests
Requires-Dist: sqlglot==27.6.0
